TaxonNamesResolver.py
setup.cfg
setup.py
taxon_names_resolver/__init__.py
taxon_names_resolver/gnr_tools.py
taxon_names_resolver/manip_tools.py
taxon_names_resolver/resolver.py
taxon_names_resolver.egg-info/PKG-INFO
taxon_names_resolver.egg-info/SOURCES.txt
taxon_names_resolver.egg-info/dependency_links.txt
taxon_names_resolver.egg-info/requires.txt
taxon_names_resolver.egg-info/top_level.txt