Metadata-Version: 1.1
Name: taxon-names-resolver
Version: 1.0.5
Summary: Resolve taxonomic names through Global Names Resolver.
Home-page: https://github.com/DomBennett/TaxonNamesResolver
Author: Dominic John Bennett
Author-email: dominic.john.bennett@gmail.com
License: LICENSE.txt
Download-URL: https://github.com/DomBennett/TaxonNamesResolver/tarball/1.0.5
Keywords: taxonomy biodiversity systematics natural history
Platform: UNKNOWN
Classifier: Development Status :: 4 - Beta
Classifier: Topic :: Scientific/Engineering :: Bio-Informatics
Classifier: Programming Language :: Python :: 2.7
Classifier: License :: OSI Approved :: GNU General Public License v2 (GPLv2)
